colouredlogs.pth
colouredlogs/__init__.py
colouredlogs/cli.py
colouredlogs/demo.py
colouredlogs/syslog.py
colouredlogs/tests.py
colouredlogs/converter/__init__.py
colouredlogs/converter/colours.py
colouredlogs-10.0.1.dist-info/LICENSE.txt
colouredlogs-10.0.1.dist-info/METADATA
colouredlogs-10.0.1.dist-info/WHEEL
colouredlogs-10.0.1.dist-info/entry_points.txt
colouredlogs-10.0.1.dist-info/top_level.txt
colouredlogs-10.0.1.dist-info/RECORD
